kazu/__init__.py
kazu/py.typed
kazu/annotation/__init__.py
kazu/annotation/acceptance_test.py
kazu/annotation/label_studio.py
kazu/conf/__init__.py
kazu/conf/config.yaml
kazu/conf/AbbreviationFinderStep/default.yaml
kazu/conf/CleanupActions/default.yaml
kazu/conf/CleanupActions/uri_stripping.yaml
kazu/conf/CleanupStep/default.yaml
kazu/conf/DictionaryEntityLinkingStep/default.yaml
kazu/conf/DisambiguationStrategies/default.yaml
kazu/conf/EntityClassDisambiguationStep/default.yaml
kazu/conf/ExplosionStringMatchingStep/default.yaml
kazu/conf/GLiNERStep/default.yaml
kazu/conf/LSWebUtils/default.yaml
kazu/conf/MappingStep/default.yaml
kazu/conf/MemoryEfficientStringMatchingStep/default.yaml
kazu/conf/MergeOverlappingEntsStep/default.yaml
kazu/conf/Middlewares/default.yaml
kazu/conf/Middlewares/jwt.yaml
kazu/conf/OpsinStep/default.yaml
kazu/conf/Pipeline/default.yaml
kazu/conf/RulesBasedEntityClassDisambiguationFilterStep/default.yaml
kazu/conf/SapbertHelper/default.yaml
kazu/conf/SapbertStringSimilarityScorer/default.yaml
kazu/conf/SciSpacyPipeline/default.yaml
kazu/conf/SethStep/default.yaml
kazu/conf/SpacyNerStep/default.yaml
kazu/conf/StanzaPipeline/default.yaml
kazu/conf/StanzaStep/default.yaml
kazu/conf/StringScorers/default.yaml
kazu/conf/SynonymGeneration/default.yaml
kazu/conf/TransformersModelForTokenClassificationNerStep/default.yaml
kazu/conf/TransformersModelForTokenClassificationNerStep/multilabel_biomedBERT.yaml
kazu/conf/autocurator/default.yaml
kazu/conf/cache_sizes/default.yaml
kazu/conf/confidence/default.yaml
kazu/conf/global_actions/default.yaml
kazu/conf/ontologies/cellosaurus.yaml
kazu/conf/ontologies/chembl.yaml
kazu/conf/ontologies/cl.yaml
kazu/conf/ontologies/clo.yaml
kazu/conf/ontologies/go_bp.yaml
kazu/conf/ontologies/go_cc.yaml
kazu/conf/ontologies/go_mf.yaml
kazu/conf/ontologies/hgnc_gene_family.yaml
kazu/conf/ontologies/hpo.yaml
kazu/conf/ontologies/mondo.yaml
kazu/conf/ontologies/ot_bio_proc.yaml
kazu/conf/ontologies/ot_disease.yaml
kazu-2.3.0.dist-info/METADATA
kazu-2.3.0.dist-info/WHEEL
kazu-2.3.0.dist-info/licenses/AUTHORS.md
kazu-2.3.0.dist-info/licenses/LICENSE
kazu-2.3.0.dist-info/RECORD
