Metadata-Version: 2.4
Name: kazu
Version: 2.3.0
Summary: Biomedical Named Entity Recognition and Entity Linking for Enterprise use cases
Project-URL: documentation, https://astrazeneca.github.io/KAZU/index.html
Project-URL: repository, https://github.com/AstraZeneca/KAZU
Project-URL: changelog, https://astrazeneca.github.io/KAZU/changelog.html
Author: AstraZeneca AI and Korea University
License-File: AUTHORS.md
License-File: LICENSE
Classifier: Intended Audience :: Healthcare Industry
Classifier: License :: OSI Approved :: Apache Software License
Classifier: Natural Language :: English
Classifier: Operating System :: OS Independent
Classifier: Programming Language :: Python :: 3 :: Only
Classifier: Topic :: Scientific/Engineering :: Medical Science Apps.
Classifier: Typing :: Typed
Requires-Python: >=3.9
Requires-Dist: cachetools>=5.2.0
Requires-Dist: cattrs>=23.2.0
Requires-Dist: diskcache>=5.4.0
Requires-Dist: hydra-core>=1.3.0
Requires-Dist: pandas
Requires-Dist: psutil>=5.3.0
Requires-Dist: pyahocorasick
Requires-Dist: pyarrow
Requires-Dist: pymongo>=4.3.3
Requires-Dist: rapidfuzz>=1.0.0
Requires-Dist: rdflib>=6.0.0
Requires-Dist: regex>=2020.1.7
Requires-Dist: requests>=2.20.0
Requires-Dist: scikit-learn>=0.24.0
Requires-Dist: scipy<1.12.0
Requires-Dist: spacy==3.7.0
Requires-Dist: torch>=2.0.0
Requires-Dist: tqdm
Requires-Dist: transformers>=4.0.0
Provides-Extra: all-steps
Requires-Dist: gliner==0.1.7; extra == 'all-steps'
Requires-Dist: py4j>=0.10.9; extra == 'all-steps'
Requires-Dist: rdkit>=2023.3.1; extra == 'all-steps'
Requires-Dist: stanza<1.6.0,>=1.0.0; extra == 'all-steps'
Provides-Extra: dev
Requires-Dist: blacken-docs; extra == 'dev'
Requires-Dist: black~=24.0; extra == 'dev'
Requires-Dist: bump2version; extra == 'dev'
Requires-Dist: fastapi==0.108.0; extra == 'dev'
Requires-Dist: flake8; extra == 'dev'
Requires-Dist: furo>=2023.08.17; extra == 'dev'
Requires-Dist: gliner==0.1.7; extra == 'dev'
Requires-Dist: google-cloud-aiplatform; extra == 'dev'
Requires-Dist: hypothesis; extra == 'dev'
Requires-Dist: mwparserfromhell; extra == 'dev'
Requires-Dist: mypy; extra == 'dev'
Requires-Dist: myst-parser; extra == 'dev'
Requires-Dist: openai; extra == 'dev'
Requires-Dist: pandas-stubs>=2.0.0; extra == 'dev'
Requires-Dist: pre-commit<4.0.0; extra == 'dev'
Requires-Dist: py4j>=0.10.9; extra == 'dev'
Requires-Dist: pydantic<2.0; extra == 'dev'
Requires-Dist: pyjwt>=2.0.0; extra == 'dev'
Requires-Dist: pytest; extra == 'dev'
Requires-Dist: pytest-cov; extra == 'dev'
Requires-Dist: pytest-mock; extra == 'dev'
Requires-Dist: pytest-timeout; extra == 'dev'
Requires-Dist: ray>=1.10.0; extra == 'dev'
Requires-Dist: ray[serve]>=2.0.0; extra == 'dev'
Requires-Dist: rdkit>=2023.3.1; extra == 'dev'
Requires-Dist: sphinx<8.0,>=7.2; extra == 'dev'
Requires-Dist: stanza<1.6.0,>=1.0.0; extra == 'dev'
Requires-Dist: streamlit; extra == 'dev'
Requires-Dist: tensorboard; extra == 'dev'
Requires-Dist: towncrier>=23.10.0; extra == 'dev'
Requires-Dist: types-cachetools; extra == 'dev'
Requires-Dist: types-docutils; extra == 'dev'
Requires-Dist: types-psutil; extra == 'dev'
Requires-Dist: types-regex; extra == 'dev'
Requires-Dist: types-requests; extra == 'dev'
Requires-Dist: types-tqdm; extra == 'dev'
Requires-Dist: vulture; extra == 'dev'
Provides-Extra: llm
Requires-Dist: google-cloud-aiplatform; extra == 'llm'
Requires-Dist: openai; extra == 'llm'
Provides-Extra: typed
Requires-Dist: pandas-stubs>=2.0.0; extra == 'typed'
Requires-Dist: types-cachetools; extra == 'typed'
Requires-Dist: types-docutils; extra == 'typed'
Requires-Dist: types-psutil; extra == 'typed'
Requires-Dist: types-regex; extra == 'typed'
Requires-Dist: types-requests; extra == 'typed'
Requires-Dist: types-tqdm; extra == 'typed'
Provides-Extra: webserver
Requires-Dist: fastapi==0.108.0; extra == 'webserver'
Requires-Dist: pydantic<2.0; extra == 'webserver'
Requires-Dist: pyjwt>=2.0.0; extra == 'webserver'
Requires-Dist: ray[serve]>=2.0.0; extra == 'webserver'
